LICENSE
MANIFEST.in
README.rst
setup.py
prospector2/__init__.py
prospector2/__main__.py
prospector2/__pkginfo__.py
prospector2/autodetect.py
prospector2/blender.py
prospector2/encoding.py
prospector2/exceptions.py
prospector2/finder.py
prospector2/message.py
prospector2/pathutils.py
prospector2/postfilter.py
prospector2/run.py
prospector2/suppression.py
prospector2.egg-info/PKG-INFO
prospector2.egg-info/SOURCES.txt
prospector2.egg-info/dependency_links.txt
prospector2.egg-info/entry_points.txt
prospector2.egg-info/not-zip-safe
prospector2.egg-info/requires.txt
prospector2.egg-info/top_level.txt
prospector2/config/__init__.py
prospector2/config/configuration.py
prospector2/config/datatype.py
prospector2/formatters/__init__.py
prospector2/formatters/base.py
prospector2/formatters/emacs.py
prospector2/formatters/grouped.py
prospector2/formatters/json.py
prospector2/formatters/pylint.py
prospector2/formatters/text.py
prospector2/formatters/vscode.py
prospector2/formatters/xunit.py
prospector2/formatters/yaml.py
prospector2/profiles/__init__.py
prospector2/profiles/profile.py
prospector2/tools/__init__.py
prospector2/tools/base.py
prospector2/tools/utils.py
prospector2/tools/dodgy/__init__.py
prospector2/tools/frosted/__init__.py
prospector2/tools/mccabe/__init__.py
prospector2/tools/pep257/__init__.py
prospector2/tools/pep8/__init__.py
prospector2/tools/profile_validator/__init__.py
prospector2/tools/pyflakes/__init__.py
prospector2/tools/pylint/__init__.py
prospector2/tools/pylint/collector.py
prospector2/tools/pylint/indent_checker.py
prospector2/tools/pylint/linter.py
prospector2/tools/pyroma/__init__.py
prospector2/tools/vulture/__init__.py