Metadata-Version: 2.1
Name: prospector2
Version: 0.1
Summary: Prospector: python static analysis tool
Home-page: http://prospector.readthedocs.io
Author: landscape.io
Author-email: code@landscape.io
License: GPLv2
Keywords: pylint pyflakes pep8 mccabe frosted prospector static code analysis
Platform: UNKNOWN
Classifier: Development Status :: 5 - Production/Stable
Classifier: Environment :: Console
Classifier: Intended Audience :: Developers
Classifier: Operating System :: Unix
Classifier: Operating System :: Microsoft :: Windows :: Windows 10
Classifier: Operating System :: MacOS :: MacOS X
Classifier: Topic :: Software Development :: Quality Assurance
Classifier: Programming Language :: Python :: 2.7
Classifier: License :: OSI Approved :: GNU General Public License v2 or later (GPLv2+)
Provides-Extra: with_frosted
Provides-Extra: with_vulture
Provides-Extra: build_tools
Provides-Extra: with_pyroma
Provides-Extra: with_everything
